cati/__init__.py
cati/__main__.py
cati/cmdline/ArgParser.py
cati/cmdline/BaseCommand.py
cati/cmdline/__init__.py
cati/cmdline/ansi.py
cati/cmdline/kernel.py
cati/cmdline/pr.py
cati/cmdline/commands/AutoremoveCommand.py
cati/cmdline/commands/CheckCommand.py
cati/cmdline/commands/ClearCacheCommand.py
cati/cmdline/commands/DownloadCommand.py
cati/cmdline/commands/FilesCommand.py
cati/cmdline/commands/FinfoCommand.py
cati/cmdline/commands/ForgetCommand.py
cati/cmdline/commands/FullUpgradeCommand.py
cati/cmdline/commands/HelpCommand.py
cati/cmdline/commands/InstallCommand.py
cati/cmdline/commands/ListCommand.py
cati/cmdline/commands/MeowCommand.py
cati/cmdline/commands/PkgCommand.py
cati/cmdline/commands/QueryCommand.py
cati/cmdline/commands/RDependsCommand.py
cati/cmdline/commands/RemoveCommand.py
cati/cmdline/commands/RepoCommand.py
cati/cmdline/commands/SearchCommand.py
cati/cmdline/commands/ShowCommand.py
cati/cmdline/commands/StateCommand.py
cati/cmdline/commands/UpdateCommand.py
cati/cmdline/commands/UpgradeCommand.py
cati/cmdline/commands/__init__.py
cati/cmdline/components/DownloadProgress.py
cati/cmdline/components/PackageShower.py
cati/cmdline/components/ReposListErrorShower.py
cati/cmdline/components/StateContentShower.py
cati/cmdline/components/TransactionShower.py
cati/cmdline/components/__init__.py
cati/dotcati/ArchiveModel.py
cati/dotcati/Builder.py
cati/dotcati/Installer.py
cati/dotcati/ListUpdater.py
cati/dotcati/PackageJsonValidator.py
cati/dotcati/Pkg.py
cati/dotcati/PkgConvertor.py
cati/dotcati/__init__.py
cati/dotcati/exceptions.py
cati/frontend/Env.py
cati/frontend/HealthChecker.py
cati/frontend/RootRequired.py
cati/frontend/SecurityBlacklist.py
cati/frontend/SysArch.py
cati/frontend/Temp.py
cati/frontend/Version.py
cati/frontend/__init__.py
cati/helpers/__init__.py
cati/helpers/hash.py
cati/repo/DirCrawler.py
cati/repo/Repo.py
cati/repo/Scanner.py
cati/repo/__init__.py
cati/repo/drivers/BaseDriver.py
cati/repo/drivers/File.py
cati-0.1a8.dist-info/LICENSE
cati-0.1a8.dist-info/METADATA
cati-0.1a8.dist-info/WHEEL
cati-0.1a8.dist-info/top_level.txt
cati-0.1a8.dist-info/RECORD
