Metadata-Version: 2.1
Name: cati
Version: 0.1a8
Summary: The Cati Unix Package manager
Home-page: https://github.com/parsampsh/gameoflife
Author: parsa shahmaleki
Author-email: parsampsh@gmail.com
License: UNKNOWN
Platform: UNKNOWN
Classifier: Programming Language :: Python :: 3
Classifier: Operating System :: Unix
Requires-Python: >=3.6
Requires-Dist: packaging (>=20.4)
Requires-Dist: requests (>=2.25.0)
Requires-Dist: wget (>=3.2)
